{
  "annotations": {
    "list": [
      {
        "builtIn": 1,
        "datasource": "grafana",
        "enable": true,
        "hide": true,
        "iconColor": "rgba(0, 211, 255, 1)",
        "name": "Annotations & Alerts",
        "target": {
          "limit": 100,
          "matchAny": false,
          "tags": [],
          "type": "dashboard"
        },
        "type": "dashboard"
      }
    ]
  },
  "description": "",
  "editable": true,
  "fiscalYearStartMonth": 0,
  "gnetId": null,
  "graphTooltip": 1,
  "links": [],
  "liveNow": false,
  "panels": [
    {
      "datasource": null,
      "gridPos": {
        "h": 1,
        "w": 24,
        "x": 0,
        "y": 0
      },
      "id": 8,
      "title": "Overview count",
      "type": "row"
    },
    {
      "datasource": "-- Dashboard --",
      "fieldConfig": {
        "defaults": {
          "color": {
            "fixedColor": "semi-dark-red",
            "mode": "thresholds"
          },
          "decimals": 0,
          "mappings": [],
          "min": 0,
          "thresholds": {
            "mode": "absolute",
            "steps": [
              {
                "color": "green",
                "value": null
              },
              {
                "color": "semi-dark-red",
                "value": 0.75
              }
            ]
          },
          "unit": "none"
        },
        "overrides": []
      },
      "gridPos": {
        "h": 6,
        "w": 8,
        "x": 0,
        "y": 1
      },
      "id": 10,
      "interval": "10m",
      "maxDataPoints": null,
      "options": {
        "colorMode": "value",
        "graphMode": "none",
        "justifyMode": "auto",
        "orientation": "auto",
        "reduceOptions": {
          "calcs": [
            "lastNotNull"
          ],
          "fields": "",
          "values": false
        },
        "text": {},
        "textMode": "auto"
      },
      "pluginVersion": "8.2.3",
      "targets": [
        {
          "panelId": 4,
          "queryType": "randomWalk",
          "refId": "A"
        }
      ],
      "title": "FAILURE",
      "transparent": true,
      "type": "stat"
    },
    {
      "datasource": "-- Dashboard --",
      "fieldConfig": {
        "defaults": {
          "color": {
            "mode": "thresholds"
          },
          "decimals": 0,
          "mappings": [],
          "min": 0,
          "thresholds": {
            "mode": "absolute",
            "steps": [
              {
                "color": "green",
                "value": null
              },
              {
                "color": "dark-yellow",
                "value": 20
              },
              {
                "color": "red",
                "value": 50
              }
            ]
          },
          "unit": "none"
        },
        "overrides": []
      },
      "gridPos": {
        "h": 6,
        "w": 8,
        "x": 8,
        "y": 1
      },
      "id": 11,
      "interval": "10m",
      "options": {
        "colorMode": "value",
        "graphMode": "none",
        "justifyMode": "auto",
        "orientation": "auto",
        "reduceOptions": {
          "calcs": [
            "lastNotNull"
          ],
          "fields": "",
          "values": false
        },
        "text": {},
        "textMode": "auto"
      },
      "pluginVersion": "8.2.3",
      "targets": [
        {
          "panelId": 5,
          "queryType": "randomWalk",
          "refId": "A"
        }
      ],
      "title": "MISCONFIGURE",
      "transparent": true,
      "type": "stat"
    },
    {
      "datasource": "-- Dashboard --",
      "fieldConfig": {
        "defaults": {
          "color": {
            "mode": "thresholds"
          },
          "decimals": 0,
          "mappings": [],
          "min": 0,
          "thresholds": {
            "mode": "absolute",
            "steps": [
              {
                "color": "green",
                "value": null
              }
            ]
          },
          "unit": "none"
        },
        "overrides": []
      },
      "gridPos": {
        "h": 6,
        "w": 8,
        "x": 16,
        "y": 1
      },
      "id": 12,
      "interval": "10m",
      "options": {
        "colorMode": "value",
        "graphMode": "none",
        "justifyMode": "auto",
        "orientation": "auto",
        "reduceOptions": {
          "calcs": [
            "lastNotNull"
          ],
          "fields": "",
          "values": false
        },
        "text": {},
        "textMode": "auto"
      },
      "pluginVersion": "8.2.3",
      "targets": [
        {
          "panelId": 6,
          "queryType": "randomWalk",
          "refId": "A"
        }
      ],
      "title": "OPEN",
      "transparent": true,
      "type": "stat"
    },
    {
      "datasource": "elasticsearch",
      "fieldConfig": {
        "defaults": {
          "color": {
            "fixedColor": "semi-dark-red",
            "mode": "fixed"
          },
          "custom": {
            "axisLabel": "",
            "axisPlacement": "hidden",
            "axisSoftMin": 0,
            "fillOpacity": 50,
            "gradientMode": "none",
            "hideFrom": {
              "legend": false,
              "tooltip": false,
              "viz": false
            },
            "lineWidth": 1
          },
          "decimals": 0,
          "mappings": [],
          "thresholds": {
            "mode": "absolute",
            "steps": [
              {
                "color": "green",
                "value": null
              }
            ]
          },
          "unit": "none"
        },
        "overrides": []
      },
      "gridPos": {
        "h": 7,
        "w": 12,
        "x": 0,
        "y": 7
      },
      "id": 14,
      "interval": "10m",
      "links": [],
      "options": {
        "barWidth": 0.75,
        "groupWidth": 0.7,
        "legend": {
          "calcs": [],
          "displayMode": "hidden",
          "placement": "bottom"
        },
        "orientation": "vertical",
        "showValue": "auto",
        "stacking": "none",
        "text": {},
        "tooltip": {
          "mode": "single"
        }
      },
      "pluginVersion": "8.0.6",
      "targets": [
        {
          "alias": "",
          "bucketAggs": [
            {
              "field": "connection-type.keyword",
              "id": "5",
              "settings": {
                "min_doc_count": "0",
                "order": "desc",
                "orderBy": "3",
                "size": "0"
              },
              "type": "terms"
            },
            {
              "field": "@timestamp",
              "id": "6",
              "settings": {
                "interval": "auto",
                "min_doc_count": "0",
                "trimEdges": "1"
              },
              "type": "date_histogram"
            }
          ],
          "metrics": [
            {
              "id": "3",
              "type": "count"
            }
          ],
          "query": "ditto-log-tag.keyword:connection-live-status-failed",
          "queryType": "randomWalk",
          "refId": "A",
          "timeField": "@timestamp"
        }
      ],
      "timeFrom": null,
      "timeShift": null,
      "title": "Failures per connection type",
      "transformations": [
        {
          "id": "reduce",
          "options": {
            "includeTimeField": false,
            "mode": "seriesToRows",
            "reducers": [
              "lastNotNull"
            ]
          }
        }
      ],
      "transparent": true,
      "type": "barchart"
    },
    {
      "datasource": "elasticsearch",
      "fieldConfig": {
        "defaults": {
          "color": {
            "mode": "palette-classic"
          },
          "custom": {
            "axisLabel": "",
            "axisPlacement": "hidden",
            "axisSoftMin": 0,
            "fillOpacity": 50,
            "gradientMode": "none",
            "hideFrom": {
              "legend": false,
              "tooltip": false,
              "viz": false
            },
            "lineWidth": 1
          },
          "decimals": 0,
          "mappings": [],
          "thresholds": {
            "mode": "absolute",
            "steps": [
              {
                "color": "green",
                "value": null
              },
              {
                "color": "#EAB839",
                "value": 20
              },
              {
                "color": "red",
                "value": 50
              }
            ]
          },
          "unit": "none"
        },
        "overrides": []
      },
      "gridPos": {
        "h": 7,
        "w": 12,
        "x": 12,
        "y": 7
      },
      "id": 15,
      "interval": "10m",
      "links": [],
      "options": {
        "barWidth": 0.76,
        "groupWidth": 0.7,
        "legend": {
          "calcs": [],
          "displayMode": "hidden",
          "placement": "bottom"
        },
        "orientation": "vertical",
        "showValue": "auto",
        "stacking": "none",
        "text": {},
        "tooltip": {
          "mode": "single"
        }
      },
      "pluginVersion": "8.0.6",
      "targets": [
        {
          "alias": "",
          "bucketAggs": [
            {
              "field": "connection-type.keyword",
              "id": "5",
              "settings": {
                "min_doc_count": "0",
                "order": "desc",
                "orderBy": "3",
                "size": "0"
              },
              "type": "terms"
            },
            {
              "field": "@timestamp",
              "id": "6",
              "settings": {
                "interval": "auto",
                "min_doc_count": "0",
                "trimEdges": "1"
              },
              "type": "date_histogram"
            }
          ],
          "metrics": [
            {
              "id": "3",
              "type": "count"
            }
          ],
          "query": "ditto-log-tag.keyword:connection-live-status-misconfigured",
          "queryType": "randomWalk",
          "refId": "A",
          "timeField": "@timestamp"
        }
      ],
      "timeFrom": null,
      "timeShift": null,
      "title": "Misconfigured per connection type",
      "transformations": [
        {
          "id": "reduce",
          "options": {
            "includeTimeField": false,
            "mode": "seriesToRows",
            "reducers": [
              "lastNotNull"
            ]
          }
        }
      ],
      "transparent": true,
      "type": "barchart"
    },
    {
      "datasource": null,
      "gridPos": {
        "h": 1,
        "w": 24,
        "x": 0,
        "y": 14
      },
      "id": 2,
      "title": "Live status",
      "type": "row"
    },
    {
      "datasource": "elasticsearch",
      "fieldConfig": {
        "defaults": {
          "color": {
            "fixedColor": "semi-dark-red",
            "mode": "fixed"
          },
          "custom": {
            "axisLabel": "",
            "axisPlacement": "auto",
            "axisSoftMin": 0,
            "barAlignment": 0,
            "drawStyle": "line",
            "fillOpacity": 75,
            "gradientMode": "none",
            "hideFrom": {
              "legend": false,
              "tooltip": false,
              "viz": false
            },
            "lineInterpolation": "smooth",
            "lineStyle": {
              "fill": "solid"
            },
            "lineWidth": 1,
            "pointSize": 6,
            "scaleDistribution": {
              "type": "linear"
            },
            "showPoints": "always",
            "spanNulls": false,
            "stacking": {
              "group": "A",
              "mode": "none"
            },
            "thresholdsStyle": {
              "mode": "line"
            }
          },
          "decimals": 0,
          "links": [],
          "mappings": [],
          "min": 0,
          "thresholds": {
            "mode": "absolute",
            "steps": [
              {
                "color": "transparent",
                "value": null
              }
            ]
          },
          "unit": "none"
        },
        "overrides": []
      },
      "gridPos": {
        "h": 8,
        "w": 24,
        "x": 0,
        "y": 15
      },
      "id": 4,
      "interval": "10m",
      "links": [
        {
          "targetBlank": true,
          "title": "Show FAILUREs in Kibana",
          "url": "../kibana/app/discover#/?_g=(filters:!(),refreshInterval:(pause:!t,value:0),time:(from:now-360m,to:now))&_a=(columns:!(connection-type,connection-id,message),filters:!(),interval:auto,query:(language:lucene,query:'ditto-log-tag.keyword:connection-live-status-failed'),sort:!(!('@timestamp',desc)))"
        }
      ],
      "options": {
        "legend": {
          "calcs": [
            "mean",
            "lastNotNull"
          ],
          "displayMode": "list",
          "placement": "bottom"
        },
        "tooltip": {
          "mode": "single"
        }
      },
      "pluginVersion": "8.0.6",
      "targets": [
        {
          "alias": "Failures",
          "bucketAggs": [
            {
              "field": "@timestamp",
              "id": "1",
              "settings": {
                "interval": "auto",
                "offset": "0",
                "trimEdges": "1"
              },
              "type": "date_histogram"
            }
          ],
          "hide": false,
          "metrics": [
            {
              "id": "3",
              "type": "count"
            }
          ],
          "query": "ditto-log-tag.keyword:connection-live-status-failed",
          "queryType": "randomWalk",
          "refId": "A",
          "timeField": "@timestamp"
        },
        {
          "alias": "Failures",
          "bucketAggs": [
            {
              "field": "connection-id.keyword",
              "id": "4",
              "settings": {
                "min_doc_count": "1",
                "order": "desc",
                "orderBy": "_term",
                "size": "10"
              },
              "type": "terms"
            },
            {
              "field": "@timestamp",
              "id": "1",
              "settings": {
                "interval": "auto",
                "min_doc_count": "0",
                "offset": "0",
                "trimEdges": "1"
              },
              "type": "date_histogram"
            }
          ],
          "hide": false,
          "metrics": [
            {
              "id": "3",
              "type": "count"
            }
          ],
          "query": "ditto-log-tag.keyword:connection-live-status-failed",
          "queryType": "randomWalk",
          "refId": "B",
          "timeField": "@timestamp"
        }
      ],
      "thresholds": [
        {
          "colorMode": "critical",
          "op": "gt",
          "value": 0,
          "visible": true
        }
      ],
      "timeFrom": null,
      "timeShift": null,
      "title": "FAILUREs",
      "transparent": true,
      "type": "timeseries"
    },
    {
      "datasource": "elasticsearch",
      "fieldConfig": {
        "defaults": {
          "color": {
            "mode": "palette-classic"
          },
          "custom": {
            "axisLabel": "",
            "axisPlacement": "auto",
            "axisSoftMin": 0,
            "barAlignment": 0,
            "drawStyle": "line",
            "fillOpacity": 25,
            "gradientMode": "none",
            "hideFrom": {
              "legend": false,
              "tooltip": false,
              "viz": false
            },
            "lineInterpolation": "smooth",
            "lineWidth": 1,
            "pointSize": 6,
            "scaleDistribution": {
              "type": "linear"
            },
            "showPoints": "always",
            "spanNulls": false,
            "stacking": {
              "group": "A",
              "mode": "none"
            },
            "thresholdsStyle": {
              "mode": "line"
            }
          },
          "decimals": 0,
          "mappings": [],
          "min": 0,
          "thresholds": {
            "mode": "absolute",
            "steps": [
              {
                "color": "green",
                "value": null
              },
              {
                "color": "dark-yellow",
                "value": 20
              },
              {
                "color": "red",
                "value": 50
              }
            ]
          },
          "unit": "none"
        },
        "overrides": []
      },
      "gridPos": {
        "h": 7,
        "w": 24,
        "x": 0,
        "y": 23
      },
      "id": 5,
      "interval": "10m",
      "links": [
        {
          "targetBlank": true,
          "title": "Show MISCONFIGUREDs in Kibana",
          "url": "../kibana/app/discover#/?_g=(filters:!(),refreshInterval:(pause:!t,value:0),time:(from:now-360m,to:now))&_a=(columns:!(connection-type,connection-id,message),filters:!(),interval:auto,query:(language:lucene,query:'ditto-log-tag.keyword:connection-live-status-misconfigured'),sort:!(!('@timestamp',desc)))"
        }
      ],
      "options": {
        "legend": {
          "calcs": [
            "mean",
            "lastNotNull"
          ],
          "displayMode": "list",
          "placement": "bottom"
        },
        "tooltip": {
          "mode": "single"
        }
      },
      "pluginVersion": "8.0.6",
      "targets": [
        {
          "alias": "Misconfigured",
          "bucketAggs": [
            {
              "field": "@timestamp",
              "id": "1",
              "settings": {
                "interval": "auto",
                "offset": "0",
                "trimEdges": "1"
              },
              "type": "date_histogram"
            }
          ],
          "metrics": [
            {
              "id": "3",
              "type": "count"
            }
          ],
          "query": "ditto-log-tag.keyword:connection-live-status-misconfigured",
          "queryType": "randomWalk",
          "refId": "A",
          "timeField": "@timestamp"
        }
      ],
      "timeFrom": null,
      "timeShift": null,
      "title": "MISCONFIGUREDs",
      "transparent": true,
      "type": "timeseries"
    },
    {
      "datasource": "elasticsearch",
      "fieldConfig": {
        "defaults": {
          "color": {
            "mode": "palette-classic"
          },
          "custom": {
            "axisLabel": "",
            "axisPlacement": "auto",
            "axisSoftMin": 0,
            "barAlignment": 0,
            "drawStyle": "line",
            "fillOpacity": 10,
            "gradientMode": "none",
            "hideFrom": {
              "legend": false,
              "tooltip": false,
              "viz": false
            },
            "lineInterpolation": "smooth",
            "lineWidth": 1,
            "pointSize": 6,
            "scaleDistribution": {
              "type": "linear"
            },
            "showPoints": "always",
            "spanNulls": false,
            "stacking": {
              "group": "A",
              "mode": "none"
            },
            "thresholdsStyle": {
              "mode": "off"
            }
          },
          "decimals": 0,
          "mappings": [],
          "min": 0,
          "thresholds": {
            "mode": "absolute",
            "steps": [
              {
                "color": "green",
                "value": null
              },
              {
                "color": "red",
                "value": 80
              }
            ]
          },
          "unit": "none"
        },
        "overrides": []
      },
      "gridPos": {
        "h": 6,
        "w": 24,
        "x": 0,
        "y": 30
      },
      "id": 6,
      "interval": "10m",
      "links": [
        {
          "targetBlank": true,
          "title": "Show OPEN/CLOSED/UNKNOWNs in Kibana",
          "url": "../kibana/app/discover#/?_g=(filters:!(),refreshInterval:(pause:!t,value:0),time:(from:now-360m,to:now))&_a=(columns:!(connection-type,connection-id,message),filters:!(),interval:auto,query:(language:lucene,query:'ditto-log-tag.keyword:connection-live-status-open'),sort:!(!('@timestamp',desc)))"
        }
      ],
      "options": {
        "legend": {
          "calcs": [
            "mean",
            "lastNotNull"
          ],
          "displayMode": "list",
          "placement": "bottom"
        },
        "tooltip": {
          "mode": "single"
        }
      },
      "pluginVersion": "8.0.6",
      "targets": [
        {
          "alias": "Open",
          "bucketAggs": [
            {
              "field": "@timestamp",
              "id": "1",
              "settings": {
                "interval": "auto",
                "offset": "0",
                "trimEdges": "1"
              },
              "type": "date_histogram"
            }
          ],
          "metrics": [
            {
              "id": "3",
              "type": "count"
            }
          ],
          "query": "ditto-log-tag.keyword:connection-live-status-open",
          "queryType": "randomWalk",
          "refId": "A",
          "timeField": "@timestamp"
        }
      ],
      "timeFrom": null,
      "timeShift": null,
      "title": "OPENs",
      "transparent": true,
      "type": "timeseries"
    }
  ],
  "refresh": "",
  "schemaVersion": 31,
  "style": "dark",
  "tags": [
    "email"
  ],
  "templating": {
    "list": []
  },
  "time": {
    "from": "now-6h",
    "to": "now"
  },
  "timepicker": {
    "hidden": false,
    "nowDelay": "",
    "refresh_intervals": [
      "5s",
      "10s",
      "30s",
      "1m",
      "5m",
      "15m",
      "30m",
      "1h",
      "2h",
      "1d"
    ]
  },
  "timezone": "",
  "title": "Connectivity live status",
  "uid": "aCd3oqHua",
  "version": 1
}
